{"@ProxyMTProto": [], "@ProxyHagh": [], "@iproxy": [], "@iRoProxy": ["https://t.me/proxy?server=103.69.224.173&port=777&secret=eeRighJJvXrFGRMCIMJdCQ", "https://t.me/proxy?server=103.69.224.194&port=777&secret=eeRighJJvXrFGRMCIMJdCQ", "https://t.me/proxy?server=103.69.224.173&port=777&secret=eeRighJJvXrFGRMCIMJdCQ", "https://t.me/proxy?server=103.69.224.194&port=777&secret=eeRighJJvXrFGRMCIMJdCQ"], "@PinkProxy": ["https://t.me/proxy?server=94.177.51.10&port=8443&secret=7HQighJPBNMYVRNB6tdkVw", "https://t.me/proxy?server=94.177.51.10&port=8443&secret=7HQighJPBNMYVRNB6tdkVw"], "@ProxyDaemi": [], "@Myporoxy": [], "@proxyforopeta": []}