{"@ProxyMTProto": [], "@ProxyHagh": [], "@iproxy": [], "@iRoProxy": [], "@PinkProxy": [], "@ProxyDaemi": ["https://t.me/proxy?server=178.62.213.238&port=777&secret=7HQighJPBNMYVRNB6tdkVw", "https://t.me/proxy?server=103.69.224.122&port=66&secret=7HQighJPBNMYVRNB6tdkVw"], "@Myporoxy": ["https://t.me/proxy?server=Dash.Cloudflare.com.www.google.com.hercoll.pw&port=1919&secret=7HQighJPBNMYVRNB6tdkVw", "https://t.me/proxy?server=Dash.Cloudflare.com.www.google.com.hercoll.pw&port=1919&secret=7HQighJPBNMYVRNB6tdkVw", "https://t.me/proxy?server=One.Dash.cloudflare.com.www.play.google.com.avoxano.shop&port=1919&secret=7HQighJPBNMYVRNB6tdkVw", "https://t.me/proxy?server=Dash.Cloudflare.com.www.google.com.hercoll.pw&port=1919&secret=7HQighJPBNMYVRNB6tdkVw", "https://t.me/proxy?server=Site.cloudflare.com.www.play.com.dorkamos.baby&port=1919&secret=7HQighJPBNMYVRNB6tdkVw", "https://t.me/proxy?server=One.Dash.cloudflare.com.www.play.google.com.avoxano.shop&port=1919&secret=7HQighJPBNMYVRNB6tdkVw", "https://t.me/proxy?server=Dash.Cloudflare.com.www.google.com.hercoll.pw&port=1919&secret=7HQighJPBNMYVRNB6tdkVw", "https://t.me/proxy?server=Site.cloudflare.com.www.play.com.dorkamos.baby&port=1919&secret=7HQighJPBNMYVRNB6tdkVw"], "@proxyforopeta": []}